phenopackets/__init__.py
phenopackets/schema/v1/base_pb2.py
phenopackets/schema/v1/base_pb2.pyi
phenopackets/schema/v1/interpretation_pb2.py
phenopackets/schema/v1/interpretation_pb2.pyi
phenopackets/schema/v1/phenopackets_pb2.py
phenopackets/schema/v1/phenopackets_pb2.pyi
phenopackets/schema/v2/__init__.py
phenopackets/schema/v2/phenopackets_pb2.py
phenopackets/schema/v2/phenopackets_pb2.pyi
phenopackets/schema/v2/core/base_pb2.py
phenopackets/schema/v2/core/base_pb2.pyi
phenopackets/schema/v2/core/biosample_pb2.py
phenopackets/schema/v2/core/biosample_pb2.pyi
phenopackets/schema/v2/core/disease_pb2.py
phenopackets/schema/v2/core/disease_pb2.pyi
phenopackets/schema/v2/core/genome_pb2.py
phenopackets/schema/v2/core/genome_pb2.pyi
phenopackets/schema/v2/core/individual_pb2.py
phenopackets/schema/v2/core/individual_pb2.pyi
phenopackets/schema/v2/core/interpretation_pb2.py
phenopackets/schema/v2/core/interpretation_pb2.pyi
phenopackets/schema/v2/core/measurement_pb2.py
phenopackets/schema/v2/core/measurement_pb2.pyi
phenopackets/schema/v2/core/medical_action_pb2.py
phenopackets/schema/v2/core/medical_action_pb2.pyi
phenopackets/schema/v2/core/meta_data_pb2.py
phenopackets/schema/v2/core/meta_data_pb2.pyi
phenopackets/schema/v2/core/pedigree_pb2.py
phenopackets/schema/v2/core/pedigree_pb2.pyi
phenopackets/schema/v2/core/phenotypic_feature_pb2.py
phenopackets/schema/v2/core/phenotypic_feature_pb2.pyi
phenopackets/vrs/v1/vrs_pb2.py
phenopackets/vrs/v1/vrs_pb2.pyi
phenopackets/vrsatile/v1/vrsatile_pb2.py
phenopackets/vrsatile/v1/vrsatile_pb2.pyi
phenopackets-2.0.2.post5.dist-info/licenses/LICENSE
phenopackets-2.0.2.post5.dist-info/METADATA
phenopackets-2.0.2.post5.dist-info/WHEEL
phenopackets-2.0.2.post5.dist-info/top_level.txt
phenopackets-2.0.2.post5.dist-info/RECORD
