Metadata-Version: 2.4
Name: phenopackets
Version: 2.0.2.post5
Summary: Phenopacket Schema
Author-email: Michael Gargano <michael.gargano@jax.org>, Daniel Danis <daniel.gordon.danis@protonmail.com>, Jules Jacobsen <j.jacobsen@qmul.ac.uk>, Chris Mungall <cjmungall@lbl.gov>, Peter Robinson <peter.robinson@bih-charite.de>
License: BSD 3-Clause License
Project-URL: homepage, https://github.com/phenopackets/phenopacket-schema
Project-URL: repository, https://github.com/phenopackets/phenopacket-schema.git
Project-URL: documentation, https://github.com/phenopackets/phenopacket-schema
Project-URL: bugtracker, https://github.com/phenopackets/phenopacket-schema/issues
Keywords: Global Alliance for Genomics and Health,GA4GH Phenopacket Schema,GA4GH
Classifier: Development Status :: 5 - Production/Stable
Classifier: License :: OSI Approved :: MIT License
Classifier: Operating System :: OS Independent
Classifier: Programming Language :: Python :: 3.8
Classifier: Programming Language :: Python :: 3.9
Classifier: Programming Language :: Python :: 3.10
Classifier: Programming Language :: Python :: 3.11
Classifier: Programming Language :: Python :: 3.12
Requires-Python: >=3.8
License-File: LICENSE
Requires-Dist: protobuf<7.0.0,>=3.20.2
Provides-Extra: test
Requires-Dist: pytest<8.0.0,>=7.0.0; extra == "test"
Dynamic: license-file
